crazy_tiger/__init__.py
crazy_tiger/generator.py
crazy_tiger/words.py
crazy_tiger-0.1.0.dist-info/LICENSE
crazy_tiger-0.1.0.dist-info/METADATA
crazy_tiger-0.1.0.dist-info/WHEEL
crazy_tiger-0.1.0.dist-info/top_level.txt
crazy_tiger-0.1.0.dist-info/RECORD
