Metadata-Version: 2.1
Name: crazy-tiger
Version: 0.1.0
Summary: Generate harmless random nicknames
Home-page: https://github.com/jvamvas/crazy_tiger
Author: Jannis Vamvas
Author-email: jannis.vamvas@gmail.com
License: UNKNOWN
Platform: UNKNOWN
Classifier: Programming Language :: Python :: 3
Classifier: License :: OSI Approved :: The Unlicense (Unlicense)
Classifier: Operating System :: OS Independent
Classifier: Natural Language :: English
Requires-Python: >=3.6
License-File: LICENSE
